README.md
setup.py
cubepay/__init__.py
cubepay/client.py
cubepay/http_request.py
cubepay/signature.py
cubepay.egg-info/PKG-INFO
cubepay.egg-info/SOURCES.txt
cubepay.egg-info/dependency_links.txt
cubepay.egg-info/requires.txt
cubepay.egg-info/top_level.txt