Metadata-Version: 1.0
Name: cubepay
Version: 1.0.3
Summary: CubePay API library for Python, a third-party cryptocurrency payment gateway. https://cubepay.io
Home-page: https://github.com/CubePayIO/cubepay-python
Author: CubePayIO
Author-email: service@cubepay.io
License: UNKNOWN
Platform: UNKNOWN
